{
  "Ads": [
    {
      "select_main_ads": "ADMOB",
      "select_backup_ads":"APPLOVIN-M",
      "main_ads_banner": "ca-app-pub-1392303023503660/3681627816",
      "main_ads_intertitial":"ca-app-pub-1392303023503660/4994709488",
      "backup_ads_banner":"bf240ad8fabcf4bd",
      "backup_ads_intertitial":"ce43b0c3bb1f60dc",
      "interval_intertitial": 0,
      "initialize_sdk":"",
      "initialize_sdk_backup_ads":"",
      "base_url":"https://app.asynsa.com/coloring/funny-coloring/api/",
      "upload_url":"https://app.asynsa.com/coloring/funny-coloring/uploads/",
      "protect_app":"false",
      "base_64_license_key":"",
      
      "high_paying_keyword_1": "",
      "high_paying_keyword_2": "",
      "high_paying_keyword_3": "",
      "high_paying_keyword_4": "",
      "high_paying_keyword_5": "",
      "status_app": true,
      "link_redirect": "https://play.google.com/store/apps/details?id=com.aliendroid.bestcoloringsuperhero"
    }
  ]
}
